encrypta/__init__.py
encrypta/encrypta.py
encrypta/config/__init__.py
encrypta/config/base.py
encrypto/__init__.py
encrypto/encrypto.py
encrypto/config/__init__.py
encrypto/config/base.py
encrypta-1.0.0.dist-info/METADATA
encrypta-1.0.0.dist-info/WHEEL
encrypta-1.0.0.dist-info/top_level.txt
encrypta-1.0.0.dist-info/RECORD
